Moss/IntrctPeaks.py
Moss/Moss.ico
Moss/Moss.svg
Moss/MossGui.py
Moss/__init__.py
Moss/peak_shape.py
mossba-0.1.4.dev5.dist-info/LICENSE.txt
mossba-0.1.4.dev5.dist-info/METADATA
mossba-0.1.4.dev5.dist-info/WHEEL
mossba-0.1.4.dev5.dist-info/entry_points.txt
mossba-0.1.4.dev5.dist-info/top_level.txt
mossba-0.1.4.dev5.dist-info/RECORD
