Metadata-Version: 2.1
Name: mossba
Version: 0.1.4.dev5
Summary: Fit mossbauer
Home-page: https://github.com/Prestipino/Moss
Author: C. Prestipino
Author-email: cprest6@univ-univ-rennes1.fr
License: LICENSE.txt
Platform: UNKNOWN
Classifier: Programming Language :: Python :: 3
Classifier: License :: OSI Approved :: MIT License
Classifier: Operating System :: OS Independent
Requires-Python: >=3.6
Requires-Dist: scipy (>=1.2)
Requires-Dist: numpy (>=1.12)
Requires-Dist: matplotlib (>=3.0)
Requires-Dist: lmfit (>=1.0)
Requires-Dist: uncertainties (>=3.1)
Requires-Dist: pyshortcuts (>=1.7)
Requires-Dist: pyqt5
